{"type": "FeatureCollection", "features": [{"type": "Feature", "properties": {}, "geometry": {"type": "LineString", "coordinates": [[120.08458, 23.21694], [120.08966, 23.21093], [120.08672, 23.19072], [120.08862, 23.19073], [120.09248, 23.19151], [120.09729, 23.16986], [120.08901, 23.1524], [120.09145, 23.15246], [120.09934, 23.15231], [120.10702, 23.15362], [120.10458, 23.15306], [120.10671, 23.15258], [120.10914, 23.14676], [120.11358, 23.1384], [120.11723, 23.13728], [120.13065, 23.13465], [120.13274, 23.134], [120.13466, 23.13637], [120.13657, 23.13861], [120.13922, 23.14076], [120.14205, 23.14302], [120.14577, 23.14606], [120.14986, 23.1489], [120.16515, 23.1577], [120.17057, 23.15868], [120.17472, 23.16116], [120.17735, 23.16312]]}}, {"type": "Feature", "properties": {"\u7ad9\u724c\u540d\u7a31": "\u99ac\u6c99\u6e9d\u904a\u61a9\u5340", "\u7ad9\u724c\u82f1\u6587": "Mashagou Recreation Area", "\u8a9e\u97f3\u67e5\u8a62\u4ee3\u78bc": "3153"}, "geometry": {"type": "Point", "coordinates": [120.08458, 23.21694]}}, {"type": "Feature", "properties": {"\u7ad9\u724c\u540d\u7a31": "\u5c07\u8ecd\u6f01\u6e2f", "\u7ad9\u724c\u82f1\u6587": "Jiangjyun Fish Port", "\u8a9e\u97f3\u67e5\u8a62\u4ee3\u78bc": "3154"}, "geometry": {"type": "Point", "coordinates": [120.08966, 23.21093]}}, {"type": "Feature", "properties": {"\u7ad9\u724c\u540d\u7a31": "\u9be4\u9bd3\u6e2f", "\u7ad9\u724c\u82f1\u6587": "Kunsheng Harbor", "\u8a9e\u97f3\u67e5\u8a62\u4ee3\u78bc": "7804"}, "geometry": {"type": "Point", "coordinates": [120.08672, 23.19072]}}, {"type": "Feature", "properties": {"\u7ad9\u724c\u540d\u7a31": "\u9752\u9be4\u9bd3", "\u7ad9\u724c\u82f1\u6587": "Cingkunshen", "\u8a9e\u97f3\u67e5\u8a62\u4ee3\u78bc": "7805"}, "geometry": {"type": "Point", "coordinates": [120.08862, 23.19073]}}, {"type": "Feature", "properties": {"\u7ad9\u724c\u540d\u7a31": "\u9752\u9be4\u9bd3\u524d", "\u7ad9\u724c\u82f1\u6587": "Cingkunshencian", "\u8a9e\u97f3\u67e5\u8a62\u4ee3\u78bc": "7806"}, "geometry": {"type": "Point", "coordinates": [120.09248, 23.19151]}}, {"type": "Feature", "properties": {"\u7ad9\u724c\u540d\u7a31": "\u897f\u5bee", "\u7ad9\u724c\u82f1\u6587": "Siliao", "\u8a9e\u97f3\u67e5\u8a62\u4ee3\u78bc": "7843"}, "geometry": {"type": "Point", "coordinates": [120.09729, 23.16986]}}, {"type": "Feature", "properties": {"\u7ad9\u724c\u540d\u7a31": "\u53f0\u5340", "\u7ad9\u724c\u82f1\u6587": "Taicyu", "\u8a9e\u97f3\u67e5\u8a62\u4ee3\u78bc": "7844"}, "geometry": {"type": "Point", "coordinates": [120.08901, 23.1524]}}, {"type": "Feature", "properties": {"\u7ad9\u724c\u540d\u7a31": "\u65b0\u5c71\u5b50\u5bee", "\u7ad9\u724c\u82f1\u6587": "Sinshanzihliao", "\u8a9e\u97f3\u67e5\u8a62\u4ee3\u78bc": "7845"}, "geometry": {"type": "Point", "coordinates": [120.09145, 23.15246]}}, {"type": "Feature", "properties": {"\u7ad9\u724c\u540d\u7a31": "\u4e03\u80a1\u9e7d\u5c71", "\u7ad9\u724c\u82f1\u6587": "Cigu Salt Mountain", "\u8a9e\u97f3\u67e5\u8a62\u4ee3\u78bc": "7846"}, "geometry": {"type": "Point", "coordinates": [120.09934, 23.15231]}}, {"type": "Feature", "properties": {"\u7ad9\u724c\u540d\u7a31": "\u81e8\u6642\u62db\u547c\u7ad9", "\u7ad9\u724c\u82f1\u6587": "Temporary stop", "\u8a9e\u97f3\u67e5\u8a62\u4ee3\u78bc": "0001"}, "geometry": {"type": "Point", "coordinates": [120.10702, 23.15362]}}, {"type": "Feature", "properties": {"\u7ad9\u724c\u540d\u7a31": "\u9e7d\u7530\u65c5\u670d\u7ad9", "\u7ad9\u724c\u82f1\u6587": "Salt Field tourist service center", "\u8a9e\u97f3\u67e5\u8a62\u4ee3\u78bc": "9933"}, "geometry": {"type": "Point", "coordinates": [120.10458, 23.15306]}}, {"type": "Feature", "properties": {"\u7ad9\u724c\u540d\u7a31": "\u4e2d\u5bee\u5b50", "\u7ad9\u724c\u82f1\u6587": "Jhongliaozih", "\u8a9e\u97f3\u67e5\u8a62\u4ee3\u78bc": "7847"}, "geometry": {"type": "Point", "coordinates": [120.10671, 23.15258]}}, {"type": "Feature", "properties": {"\u7ad9\u724c\u540d\u7a31": "\u6c99\u5d19\u5bee", "\u7ad9\u724c\u82f1\u6587": "Shalunliao", "\u8a9e\u97f3\u67e5\u8a62\u4ee3\u78bc": "7848"}, "geometry": {"type": "Point", "coordinates": [120.10914, 23.14676]}}, {"type": "Feature", "properties": {"\u7ad9\u724c\u540d\u7a31": "\u9f8d\u5c71\u91cc", "\u7ad9\u724c\u82f1\u6587": "Longshan Vil.", "\u8a9e\u97f3\u67e5\u8a62\u4ee3\u78bc": "9930"}, "geometry": {"type": "Point", "coordinates": [120.11358, 23.1384]}}, {"type": "Feature", "properties": {"\u7ad9\u724c\u540d\u7a31": "\u6771\u9f8d\u5c71\u91cc", "\u7ad9\u724c\u82f1\u6587": "Donglongshan Vil.", "\u8a9e\u97f3\u67e5\u8a62\u4ee3\u78bc": "7849"}, "geometry": {"type": "Point", "coordinates": [120.11723, 23.13728]}}, {"type": "Feature", "properties": {"\u7ad9\u724c\u540d\u7a31": "\u4e03\u80a1\u5bee", "\u7ad9\u724c\u82f1\u6587": "Ciguliao", "\u8a9e\u97f3\u67e5\u8a62\u4ee3\u78bc": "7850"}, "geometry": {"type": "Point", "coordinates": [120.13065, 23.13465]}}, {"type": "Feature", "properties": {"\u7ad9\u724c\u540d\u7a31": "\u4e03\u80a1\u897f", "\u7ad9\u724c\u82f1\u6587": "West Cigu", "\u8a9e\u97f3\u67e5\u8a62\u4ee3\u78bc": "7851"}, "geometry": {"type": "Point", "coordinates": [120.13274, 23.134]}}, {"type": "Feature", "properties": {"\u7ad9\u724c\u540d\u7a31": "\u7389\u6210", "\u7ad9\u724c\u82f1\u6587": "Yucheng", "\u8a9e\u97f3\u67e5\u8a62\u4ee3\u78bc": "7852"}, "geometry": {"type": "Point", "coordinates": [120.13466, 23.13637]}}, {"type": "Feature", "properties": {"\u7ad9\u724c\u540d\u7a31": "\u4e94\u80a1", "\u7ad9\u724c\u82f1\u6587": "Wugu", "\u8a9e\u97f3\u67e5\u8a62\u4ee3\u78bc": "7853"}, "geometry": {"type": "Point", "coordinates": [120.13657, 23.13861]}}, {"type": "Feature", "properties": {"\u7ad9\u724c\u540d\u7a31": "\u4e03\u80a1\u516c\u6240", "\u7ad9\u724c\u82f1\u6587": "Cigu District Office", "\u8a9e\u97f3\u67e5\u8a62\u4ee3\u78bc": "7854"}, "geometry": {"type": "Point", "coordinates": [120.13922, 23.14076]}}, {"type": "Feature", "properties": {"\u7ad9\u724c\u540d\u7a31": "\u4e03\u80a1\u8fb2\u6703", "\u7ad9\u724c\u82f1\u6587": "Cigu Farmers\u2019 Assn.", "\u8a9e\u97f3\u67e5\u8a62\u4ee3\u78bc": "7855"}, "geometry": {"type": "Point", "coordinates": [120.14205, 23.14302]}}, {"type": "Feature", "properties": {"\u7ad9\u724c\u540d\u7a31": "\u4e09\u5408", "\u7ad9\u724c\u82f1\u6587": "Sanhe", "\u8a9e\u97f3\u67e5\u8a62\u4ee3\u78bc": "7856"}, "geometry": {"type": "Point", "coordinates": [120.14577, 23.14606]}}, {"type": "Feature", "properties": {"\u7ad9\u724c\u540d\u7a31": "\u5927\u5bee", "\u7ad9\u724c\u82f1\u6587": "Daliao", "\u8a9e\u97f3\u67e5\u8a62\u4ee3\u78bc": "7857"}, "geometry": {"type": "Point", "coordinates": [120.14986, 23.1489]}}, {"type": "Feature", "properties": {"\u7ad9\u724c\u540d\u7a31": "\u4f73\u91cc\u65b0\u57ce", "\u7ad9\u724c\u82f1\u6587": "Jiali Housing Complex", "\u8a9e\u97f3\u67e5\u8a62\u4ee3\u78bc": "7858"}, "geometry": {"type": "Point", "coordinates": [120.16515, 23.1577]}}, {"type": "Feature", "properties": {"\u7ad9\u724c\u540d\u7a31": "\u4f73\u91cc\u570b\u4e2d", "\u7ad9\u724c\u82f1\u6587": "Jiali Junior High School", "\u8a9e\u97f3\u67e5\u8a62\u4ee3\u78bc": "7859"}, "geometry": {"type": "Point", "coordinates": [120.17057, 23.15868]}}, {"type": "Feature", "properties": {"\u7ad9\u724c\u540d\u7a31": "\u611b\u660e\u6a4b", "\u7ad9\u724c\u82f1\u6587": "Aiming Bridge", "\u8a9e\u97f3\u67e5\u8a62\u4ee3\u78bc": "7825"}, "geometry": {"type": "Point", "coordinates": [120.17472, 23.16116]}}, {"type": "Feature", "properties": {"\u7ad9\u724c\u540d\u7a31": "\u4f73\u91cc\u7ad9", "\u7ad9\u724c\u82f1\u6587": "Jiali Bus Station", "\u8a9e\u97f3\u67e5\u8a62\u4ee3\u78bc": "7572"}, "geometry": {"type": "Point", "coordinates": [120.17735, 23.16312]}}]}